<root>
  <stock id="sh601398" symbol="">
    <recs>
      <i d="2015/4/16" t="" p="5.44" a="200" f="b" c="5" x="0.12" e="0" />
      <i d="2015/4/17" t="" p="5.72" a="200" f="s" c="5" x="1.26" e="0" />
      <i d="2015/5/4" t="" p="5.38" a="2000" f="b" c="5.38" x="1.2" e="0" />
      <i d="2015/5/6" t="" p="5.11" a="2000" f="b" c="5.11" x="1.2" e="0" />
      <i d="2015/5/11" t="" p="5.08" a="1000" f="b" c="5" x="0.6" e="0" />
      <i d="2015/5/11" t="" p="5.07" a="1000" f="b" c="5" x="0.6" e="0" />
      <i d="2015/5/13" t="" p="5.15" a="1000" f="s" c="5" x="5.75" e="0" />
      <i d="2015/5/15" t="" p="5.05" a="5000" f="b" c="12.63" x="3" e="0" />
      <i d="2015/5/22" t="" p="5.33" a="10000" f="s" c="26.65" x="59.3" e="0" />
      <i d="2017/8/29" t="" p="6.05" a="1000" f="b" c="5" x="0.12" e="0" />
      <i d="2017/10/18" t="" p="6.27" a="1000" f="s" c="5" x="6.4" e="0" />
    </recs>
    <advise />
  </stock>
  <stock id="sh600713" symbol="">
    <recs>
      <i d="2015/4/16" t="" p="12.87" a="800" f="b" c="25.74" x="0.48" e="0" />
      <i d="2015/4/17" t="" p="14.02" a="1200" f="b" c="42.06" x="0.72" e="0" />
      <i d="2015/4/22" t="" p="13.55" a="2000" f="s" c="67.75" x="28.3" e="0" />
    </recs>
    <advise />
  </stock>
  <stock id="sh601989" symbol="">
    <recs>
      <i d="2015/4/17" t="" p="13.04" a="1000" f="b" c="32.6" x="0.6" e="0" />
      <i d="2015/4/22" t="" p="14.08" a="1000" f="s" c="35.2" x="14.68" e="0" />
    </recs>
    <advise />
  </stock>
  <stock id="sh601158" symbol="">
    <recs>
      <i d="2015/4/17" t="" p="11.69" a="800" f="b" c="23.38" x="0.48" e="0" />
      <i d="2015/4/24" t="" p="10.9" a="400" f="b" c="10.9" x="0.24" e="0" />
      <i d="2015/4/28" t="" p="11.55" a="1200" f="s" c="34.65" x="14.58" e="0" />
    </recs>
    <advise />
  </stock>
  <stock id="sz000725" symbol="">
    <recs>
      <i d="2015/4/22" t="" p="4.9" a="2000" f="b" c="24.5" x="0" e="0" />
      <i d="2015/4/22" t="" p="4.85" a="2000" f="b" c="24.25" x="0" e="0" />
      <i d="2015/4/28" t="" p="4.52" a="4000" f="b" c="45.2" x="0" e="0" />
      <i d="2015/5/4" t="" p="4.73" a="8000" f="s" c="18.92" x="37.84" e="0" />
    </recs>
    <advise />
  </stock>
  <stock id="sz002266" symbol="">
    <recs>
      <i d="2015/4/22" t="" p="16.25" a="1000" f="b" c="40.63" x="0" e="0" />
      <i d="2015/4/24" t="" p="15.05" a="1000" f="b" c="37.63" x="0" e="0" />
      <i d="2015/5/14" t="" p="16" a="2000" f="s" c="16" x="32" e="0" />
    </recs>
    <advise />
  </stock>
  <stock id="sh600795" symbol="">
    <recs>
      <i d="2015/5/5" t="" p="7.36" a="3000" f="b" c="11.04" x="1.8" e="0" />
      <i d="2015/5/5" t="" p="7.02" a="2000" f="b" c="7.02" x="1.2" e="0" />
      <i d="2015/5/6" t="" p="6.68" a="5000" f="s" c="16.7" x="36.4" e="0" />
    </recs>
    <advise />
  </stock>
  <stock id="sh600664" symbol="">
    <recs>
      <i d="2015/5/6" t="" p="10.53" a="2000" f="b" c="10.53" x="1.2" e="0" />
      <i d="2015/5/11" t="" p="10.55" a="2000" f="s" c="10.55" x="22.3" e="0" />
    </recs>
    <advise />
  </stock>
  <stock id="sh600650" symbol="">
    <recs>
      <i d="2015/5/11" t="" p="21.4" a="500" f="b" c="5.35" x="0.3" e="0" />
      <i d="2015/5/12" t="" p="23.82" a="500" f="s" c="5.96" x="12.21" e="0" />
    </recs>
    <advise />
  </stock>
  <stock id="sz000088" symbol="">
    <recs>
      <i d="2015/5/12" t="" p="11.15" a="1000" f="b" c="5.58" x="0" e="0" />
      <i d="2015/5/14" t="" p="11.05" a="1000" f="b" c="5.53" x="0" e="0" />
      <i d="2015/5/22" t="" p="11.68" a="2000" f="s" c="11.68" x="23.36" e="0" />
    </recs>
    <advise />
  </stock>
  <stock id="sz002467" symbol="">
    <recs>
      <i d="2015/5/12" t="" p="18.8" a="500" f="b" c="5" x="0" e="0" />
      <i d="2015/5/13" t="" p="20.5" a="500" f="s" c="5.13" x="10.25" e="0" />
    </recs>
    <advise />
  </stock>
  <stock id="sh601390" symbol="">
    <recs>
      <i d="2015/5/13" t="" p="20.65" a="700" f="b" c="7.23" x="0.42" e="0" />
      <i d="2015/5/13" t="" p="20.2" a="300" f="b" c="5" x="0.18" e="0" />
      <i d="2015/5/14" t="" p="19.5" a="1000" f="b" c="9.75" x="0.6" e="0" />
      <i d="2015/5/15" t="" p="20.45" a="2000" f="s" c="20.45" x="42.1" e="0" />
    </recs>
    <advise />
  </stock>
  <stock id="sh601991" symbol="">
    <recs>
      <i d="2015/5/14" t="" p="7.8" a="1000" f="b" c="5" x="0.6" e="0" />
      <i d="2015/5/22" t="" p="7.92" a="1000" f="s" c="5" x="8.52" e="0" />
    </recs>
    <advise />
  </stock>
  <stock id="sh600019" symbol="">
    <recs>
      <i d="2015/5/22" t="" p="6.14" a="1000" f="b" c="5" x="0.6" e="0" />
      <i d="2015/5/26" t="" p="6.45" a="1000" f="s" c="5" x="7.05" e="0" />
      <i d="2015/9/23" t="" p="4.05" a="300" f="b" c="5" x="0.02" e="0" />
      <i d="2015/9/30" t="" p="3.77" a="300" f="s" c="5" x="1.15" e="0" />
      <i d="2015/10/14" t="" p="4" a="1000" f="b" c="5" x="0.08" e="0" />
      <i d="2015/10/16" t="" p="4.08" a="1000" f="s" c="5" x="4.16" e="0" />
    </recs>
    <advise />
  </stock>
  <stock id="sh601607" symbol="">
    <recs>
      <i d="2015/5/22" t="" p="29.4" a="200" f="b" c="5" x="0.12" e="0" />
      <i d="2015/5/25" t="" p="30.99" a="300" f="b" c="5" x="0.18" e="0" />
      <i d="2015/5/26" t="" p="31.05" a="500" f="s" c="7.76" x="15.82" e="0" />
      <i d="2015/5/28" t="" p="29.52" a="500" f="b" c="7.38" x="0.3" e="0" />
      <i d="2015/5/28" t="" p="29.15" a="500" f="b" c="7.29" x="0.3" e="0" />
      <i d="2015/5/28" t="" p="28.4" a="1000" f="b" c="14.2" x="0.6" e="0" />
      <i d="2015/6/12" t="" p="29.55" a="500" f="s" c="7.39" x="15.08" e="0" />
      <i d="2015/6/29" t="" p="23" a="600" f="b" c="6.9" x="0.36" e="0" />
      <i d="2015/7/1" t="" p="21.5" a="200" f="b" c="5" x="0.12" e="0" />
      <i d="2015/7/2" t="" p="18.95" a="200" f="b" c="5" x="0.12" e="0" />
      <i d="2015/7/7" t="" p="16.95" a="500" f="b" c="5" x="0.3" e="0" />
      <i d="2015/7/7" t="" p="17.36" a="500" f="s" c="5" x="8.98" e="0" />
      <i d="2015/7/8" t="" p="16.38" a="500" f="b" c="5" x="0.3" e="0" />
      <i d="2015/7/9" t="" p="16.5" a="500" f="s" c="5" x="8.55" e="0" />
      <i d="2015/7/9" t="" p="17.95" a="500" f="s" c="5" x="9.28" e="0" />
      <i d="2015/7/9" t="" p="17.99" a="1000" f="s" c="9" x="18.59" e="0" />
      <i d="2015/7/13" t="" p="20.94" a="500" f="b" c="5.24" x="0.3" e="0" />
      <i d="2015/7/13" t="" p="20.8" a="500" f="s" c="5.2" x="10.7" e="0" />
      <i d="2015/7/13" t="" p="21.76" a="300" f="b" c="5" x="0.18" e="0" />
      <i d="2015/7/14" t="" p="22" a="300" f="s" c="5" x="6.78" e="0" />
      <i d="2015/7/14" t="" p="21.55" a="300" f="b" c="5" x="0.18" e="0" />
      <i d="2015/7/14" t="" p="21.8" a="300" f="s" c="5" x="6.72" e="0" />
      <i d="2015/7/22" t="" p="21.93" a="500" f="b" c="5.48" x="0.3" e="0" />
      <i d="2015/7/23" t="" p="22.55" a="500" f="s" c="5.64" x="11.58" e="0" />
      <i d="2015/7/27" t="" p="21.3" a="500" f="b" c="5.33" x="0.3" e="0" />
      <i d="2015/8/4" t="" p="21.6" a="500" f="s" c="5.4" x="11.02" e="0" />
      <i d="2015/8/11" t="" p="22.05" a="200" f="b" c="5" x="0.09" e="0" />
      <i d="2015/8/13" t="" p="22.15" a="200" f="s" c="5" x="4.52" e="0" />
      <i d="2015/8/26" t="" p="17.2" a="500" f="s" c="5" x="8.77" e="0" />
      <i d="2015/8/26" t="" p="16.74" a="500" f="b" c="5" x="0.17" e="0" />
      <i d="2015/8/27" t="" p="17.05" a="500" f="s" c="5" x="8.7" e="0" />
      <i d="2015/8/27" t="" p="17.69" a="400" f="s" c="5" x="7.22" e="0" />
      <i d="2015/8/28" t="" p="18.788" a="500" f="b" c="5" x="0.19" e="0" />
      <i d="2015/8/31" t="" p="18.12" a="400" f="b" c="5" x="0.14" e="0" />
      <i d="2015/9/1" t="" p="18.66" a="400" f="s" c="5" x="7.61" e="0" />
      <i d="2015/9/2" t="" p="19.06" a="500" f="s" c="5" x="9.72" e="0" />
      <i d="2015/9/7" t="" p="18.32" a="500" f="b" c="5" x="0.18" e="0" />
      <i d="2015/9/8" t="" p="18.75" a="500" f="s" c="5" x="9.57" e="0" />
      <i d="2015/10/9" t="" p="18.5" a="400" f="b" c="5" x="0.15" e="0" />
      <i d="2015/10/13" t="" p="18.92" a="400" f="s" c="5" x="7.72" e="0" />
      <i d="2015/10/23" t="" p="20.01" a="500" f="b" c="5" x="0.2" e="0" />
      <i d="2015/11/10" t="" p="20.62" a="500" f="s" c="5.16" x="10.52" e="0" />
      <i d="2016/5/25" t="" p="18.2" a="100" f="b" c="5" x="0.04" e="0" />
      <i d="2016/5/26" t="" p="18.07" a="100" f="s" c="5" x="1.85" e="0" />
      <i d="2016/7/13" t="" p="19.406" a="500" f="b" c="5" x="0.2" e="0" />
      <i d="2016/7/14" t="" p="19.35" a="500" f="s" c="5" x="9.88" e="0" />
      <i d="2017/3/23" t="" p="23.24" a="100" f="s" c="5" x="2.37" e="0" />
    </recs>
    <advise />
  </stock>
  <stock id="sz002557" symbol="">
    <recs>
      <i d="2015/5/25" t="" p="32.1" a="500" f="b" c="8.03" x="0" e="0" />
      <i d="2015/5/26" t="" p="33.5" a="500" f="s" c="8.38" x="16.75" e="0" />
    </recs>
    <advise />
  </stock>
  <stock id="sh601006" symbol="">
    <recs>
      <i d="2015/5/27" t="" p="13.65" a="1000" f="b" c="6.83" x="0.6" e="0" />
      <i d="2015/5/28" t="" p="12.85" a="1000" f="b" c="6.43" x="0.6" e="0" />
      <i d="2015/6/4" t="" p="12.95" a="2000" f="s" c="12.95" x="27.1" e="0" />
    </recs>
    <advise />
  </stock>
  <stock id="sh601985" symbol="">
    <recs>
      <i d="2015/6/4" t="" p="3.39" a="1000" f="b" c="0" x="0" e="0" />
      <i d="2015/6/26" t="" p="13.82" a="1000" f="s" c="6.91" x="14.42" e="0" />
    </recs>
    <advise />
  </stock>
  <stock id="sh600518" symbol="">
    <recs>
      <i d="2015/6/8" t="" p="43.85" a="100" f="b" c="5" x="0.06" e="0" />
      <i d="2015/6/10" t="" p="49.36" a="100" f="s" c="5" x="5" e="0" />
    </recs>
    <advise />
  </stock>
  <stock id="sh600887" symbol="">
    <recs>
      <i d="2015/6/9" t="" p="21.38" a="200" f="b" c="5" x="0.12" e="0" />
      <i d="2015/6/12" t="" p="21.2" a="300" f="b" c="5" x="0.18" e="0" />
      <i d="2015/6/15" t="" p="20.8" a="500" f="b" c="5.2" x="0.3" e="0" />
      <i d="2015/6/15" t="" p="20.3" a="1000" f="b" c="10.15" x="0.6" e="0" />
      <i d="2015/7/1" t="" p="18.7" a="500" f="b" c="5" x="0.3" e="0" />
      <i d="2015/7/1" t="" p="19.05" a="500" f="s" c="5" x="9.83" e="0" />
      <i d="2015/7/13" t="" p="19.41" a="500" f="b" c="5" x="0.3" e="0" />
      <i d="2015/7/14" t="" p="18.54" a="300" f="b" c="5" x="0.18" e="0" />
      <i d="2015/7/22" t="" p="18.7" a="800" f="s" c="7.48" x="15.44" e="0" />
      <i d="2015/7/23" t="" p="18.42" a="300" f="b" c="5" x="0.18" e="0" />
      <i d="2015/7/23" t="" p="18.75" a="300" f="s" c="5" x="5.81" e="0" />
      <i d="2015/7/29" t="" p="16.9" a="500" f="b" c="5" x="0.3" e="0" />
      <i d="2015/7/29" t="" p="17.15" a="500" f="s" c="5" x="8.88" e="0" />
      <i d="2015/7/31" t="" p="16.85" a="500" f="b" c="5" x="0.3" e="0" />
      <i d="2015/7/31" t="" p="16.98" a="500" f="s" c="5" x="8.79" e="0" />
      <i d="2015/8/5" t="" p="17.6" a="500" f="b" c="5" x="0.18" e="0" />
      <i d="2015/8/10" t="" p="17.94" a="500" f="s" c="5" x="9.15" e="0" />
      <i d="2015/8/11" t="" p="18.05" a="500" f="b" c="5" x="0.18" e="0" />
      <i d="2015/8/13" t="" p="17.47" a="300" f="b" c="5" x="0.1" e="0" />
      <i d="2015/8/13" t="" p="17.66" a="800" f="s" c="7.06" x="14.41" e="0" />
      <i d="2015/8/18" t="" p="17.02" a="300" f="b" c="5" x="0.1" e="0" />
      <i d="2015/8/25" t="" p="13.33" a="200" f="b" c="5" x="0.05" e="0" />
      <i d="2015/8/26" t="" p="14.41" a="500" f="s" c="5" x="7.35" e="0" />
      <i d="2015/8/26" t="" p="14.52" a="1000" f="s" c="7.26" x="14.81" e="0" />
      <i d="2015/8/26" t="" p="14.52" a="500" f="s" c="5" x="7.41" e="0" />
      <i d="2015/8/27" t="" p="15.08" a="400" f="s" c="5" x="6.15" e="0" />
      <i d="2015/8/28" t="" p="15.98" a="500" f="b" c="5" x="0.16" e="0" />
      <i d="2015/8/31" t="" p="15.35" a="400" f="b" c="5" x="0.12" e="0" />
      <i d="2015/9/1" t="" p="16.19" a="400" f="s" c="5" x="6.61" e="0" />
      <i d="2015/9/2" t="" p="15.97" a="500" f="s" c="5" x="8.15" e="0" />
      <i d="2015/9/7" t="" p="15.08" a="500" f="b" c="5" x="0.15" e="0" />
      <i d="2015/9/8" t="" p="15.3" a="500" f="s" c="5" x="7.8" e="0" />
      <i d="2015/9/10" t="" p="15.8" a="500" f="b" c="5" x="0.16" e="0" />
      <i d="2015/9/16" t="" p="16.25" a="500" f="s" c="5" x="8.29" e="0" />
      <i d="2016/5/26" t="" p="15.05" a="200" f="b" c="5" x="0.06" e="0" />
      <i d="2016/5/26" t="" p="15.02" a="100" f="s" c="5" x="1.53" e="0" />
      <i d="2016/5/27" t="" p="15.13" a="200" f="b" c="5" x="0.06" e="0" />
      <i d="2016/6/1" t="" p="15.33" a="300" f="s" c="5" x="4.69" e="0" />
      <i d="2016/6/30" t="" p="16.65" a="100" f="s" c="5" x="1.7" e="0" />
    </recs>
    <advise />
  </stock>
  <stock id="sh600030" symbol="">
    <recs>
      <i d="2015/6/10" t="" p="32.69" a="100" f="b" c="5" x="0.06" e="0" />
      <i d="2015/6/11" t="" p="32.04" a="100" f="s" c="5" x="3.26" e="0" />
      <i d="2015/6/16" t="" p="31.2" a="400" f="b" c="6.24" x="0.24" e="0" />
      <i d="2015/7/1" t="" p="26.86" a="400" f="b" c="5.37" x="0.24" e="0" />
      <i d="2015/7/1" t="" p="26.6" a="200" f="b" c="5" x="0.12" e="0" />
      <i d="2015/7/6" t="" p="26.833" a="500" f="s" c="6.71" x="13.71" e="0" />
      <i d="2015/7/10" t="" p="26.48" a="500" f="b" c="6.62" x="0.3" e="0" />
      <i d="2015/7/10" t="" p="27.02" a="500" f="s" c="6.76" x="13.81" e="0" />
      <i d="2015/7/13" t="" p="27.5" a="500" f="b" c="6.88" x="0.3" e="0" />
      <i d="2015/7/24" t="" p="24.35" a="200" f="b" c="5" x="0.12" e="0" />
      <i d="2015/7/24" t="" p="23.9" a="200" f="s" c="5" x="4.9" e="0" />
      <i d="2015/7/27" t="" p="23.09" a="200" f="b" c="5" x="0.12" e="0" />
      <i d="2015/7/28" t="" p="21.9" a="300" f="b" c="5" x="0.18" e="0" />
      <i d="2015/7/28" t="" p="22.5" a="500" f="s" c="5.63" x="11.55" e="0" />
      <i d="2015/7/29" t="" p="21.45" a="500" f="b" c="5.36" x="0.3" e="0" />
      <i d="2015/7/29" t="" p="21.65" a="500" f="s" c="5.41" x="11.13" e="0" />
      <i d="2015/7/30" t="" p="21.39" a="300" f="b" c="5" x="0.18" e="0" />
      <i d="2015/7/30" t="" p="20.88" a="300" f="s" c="5" x="6.44" e="0" />
      <i d="2015/7/31" t="" p="20.75" a="500" f="b" c="5.19" x="0.3" e="0" />
      <i d="2015/7/31" t="" p="20.75" a="500" f="b" c="5.19" x="0.3" e="0" />
      <i d="2015/8/4" t="" p="21" a="1000" f="s" c="10.5" x="21.42" e="0" />
      <i d="2015/8/6" t="" p="19.89" a="500" f="b" c="5" x="0.2" e="0" />
      <i d="2015/8/7" t="" p="20.5" a="500" f="s" c="5.13" x="10.46" e="0" />
      <i d="2015/8/10" t="" p="22.31" a="500" f="s" c="5.58" x="11.38" e="0" />
      <i d="2015/8/11" t="" p="22.2" a="500" f="b" c="5.55" x="0.22" e="0" />
      <i d="2015/8/12" t="" p="22.4" a="500" f="s" c="5.6" x="11.42" e="0" />
      <i d="2015/8/14" t="" p="21.83" a="500" f="b" c="5.46" x="0.22" e="0" />
      <i d="2015/8/14" t="" p="22.42" a="500" f="s" c="5.61" x="11.43" e="0" />
      <i d="2015/8/25" t="" p="14.74" a="500" f="b" c="5" x="0.15" e="0" />
      <i d="2015/8/26" t="" p="15.1" a="500" f="s" c="5" x="7.7" e="0" />
      <i d="2015/8/26" t="" p="14.41" a="500" f="b" c="5" x="0.14" e="0" />
      <i d="2015/8/27" t="" p="14.98" a="500" f="s" c="5" x="7.64" e="0" />
      <i d="2015/8/27" t="" p="15.33" a="400" f="s" c="5" x="6.25" e="0" />
      <i d="2015/8/31" t="" p="15.16" a="500" f="b" c="5" x="0.15" e="0" />
      <i d="2015/8/31" t="" p="14.83" a="400" f="b" c="5" x="0.12" e="0" />
      <i d="2015/8/31" t="" p="14.6" a="100" f="b" c="5" x="0.03" e="0" />
      <i d="2015/9/1" t="" p="15.24" a="500" f="s" c="5" x="7.77" e="0" />
      <i d="2015/9/8" t="" p="14.94" a="500" f="s" c="5" x="7.62" e="0" />
      <i d="2017/8/28" t="" p="18.25" a="100" f="s" c="5" x="1.87" e="0" />
    </recs>
    <advise />
  </stock>
  <stock id="sz000651" symbol="">
    <recs>
      <i d="2015/7/10" t="" p="23.76" a="500" f="b" c="5.94" x="0" e="0" />
      <i d="2015/7/24" t="" p="23.9" a="500" f="b" c="5.98" x="0" e="0" />
      <i d="2015/7/24" t="" p="23.3" a="500" f="s" c="5.83" x="11.65" e="0" />
      <i d="2015/8/11" t="" p="23.55" a="500" f="b" c="5.89" x="0" e="0" />
      <i d="2015/8/12" t="" p="23.03" a="500" f="b" c="5.76" x="0" e="0" />
      <i d="2015/8/13" t="" p="22.93" a="500" f="s" c="5.73" x="11.47" e="0" />
      <i d="2015/8/14" t="" p="22.6" a="500" f="b" c="5.65" x="0" e="0" />
      <i d="2015/8/25" t="" p="17.5" a="500" f="s" c="5" x="8.75" e="0" />
      <i d="2015/8/25" t="" p="17.25" a="500" f="b" c="5" x="0" e="0" />
      <i d="2015/8/25" t="" p="17.6" a="1000" f="s" c="8.8" x="17.6" e="0" />
      <i d="2015/8/25" t="" p="16.81" a="500" f="b" c="5" x="0" e="0" />
      <i d="2015/8/26" t="" p="18.18" a="500" f="s" c="5" x="9.09" e="0" />
      <i d="2015/8/26" t="" p="18.67" a="400" f="s" c="5" x="7.46" e="0" />
      <i d="2015/8/26" t="" p="18.45" a="500" f="b" c="5" x="0" e="0" />
      <i d="2015/8/27" t="" p="18.57" a="100" f="s" c="5" x="1.86" e="0" />
      <i d="2015/8/27" t="" p="18.89" a="400" f="s" c="5" x="7.56" e="0" />
      <i d="2015/8/28" t="" p="19.66" a="500" f="b" c="5" x="0" e="0" />
      <i d="2015/8/31" t="" p="18.09" a="500" f="b" c="5" x="0" e="0" />
      <i d="2015/9/1" t="" p="18.12" a="500" f="s" c="5" x="9.06" e="0" />
      <i d="2015/9/7" t="" p="17.38" a="500" f="b" c="5" x="0" e="0" />
      <i d="2015/9/8" t="" p="17.47" a="500" f="s" c="5" x="8.73" e="0" />
      <i d="2015/9/18" t="" p="16.45" a="500" f="b" c="5" x="0" e="0" />
      <i d="2015/9/18" t="" p="16.51" a="500" f="s" c="5" x="8.26" e="0" />
      <i d="2015/9/21" t="" p="16.44" a="500" f="b" c="5" x="0" e="0" />
      <i d="2015/9/21" t="" p="16.64" a="500" f="s" c="5" x="8.32" e="0" />
      <i d="2015/9/22" t="" p="16.9" a="500" f="b" c="5" x="0" e="0" />
      <i d="2015/9/30" t="" p="16.15" a="500" f="s" c="5" x="8.08" e="0" />
      <i d="2015/10/15" t="" p="17.45" a="500" f="s" c="5" x="8.73" e="0" />
      <i d="2015/10/26" t="" p="18.07" a="500" f="b" c="5" x="0" e="0" />
      <i d="2015/11/5" t="" p="18.69" a="500" f="s" c="5" x="9.35" e="0" />
      <i d="2016/12/1" t="" p="31.31" a="100" f="s" c="5" x="3.13" e="0" />
      <i d="2016/12/2" t="" p="29.14" a="100" f="b" c="5" x="0" e="0" />
      <i d="2017/3/21" t="" p="29.93" a="100" f="s" c="5" x="2.99" e="0" />
    </recs>
    <advise />
  </stock>
  <stock id="sh600031" symbol="">
    <recs>
      <i d="2015/7/16" t="" p="7.19" a="200" f="b" c="5" x="0.12" e="0" />
      <i d="2015/7/17" t="" p="7.75" a="200" f="s" c="5" x="1.67" e="0" />
      <i d="2018/2/1" t="" p="9.05" a="500" f="b" c="5" x="0.09" e="0" />
      <i d="2018/2/9" t="" p="8.1" a="500" f="b" c="5" x="0.08" e="0" />
      <i d="2018/2/26" t="" p="8.8" a="500" f="s" c="5" x="4.49" e="0" />
      <i d="2018/2/27" t="" p="8.6" a="500" f="b" c="5" x="0.09" e="0" />
      <i d="2018/2/28" t="" p="8.33" a="500" f="b" c="5" x="0.08" e="0" />
      <i d="2018/3/6" t="" p="8.44" a="500" f="s" c="5" x="4.3" e="0" />
    </recs>
    <advise />
  </stock>
  <stock id="sz002241" symbol="">
    <recs>
      <i d="2015/8/4" t="" p="31.1" a="100" f="b" c="5" x="0" e="0" />
      <i d="2015/8/5" t="" p="30" a="100" f="b" c="5" x="0" e="0" />
      <i d="2015/8/6" t="" p="29.3" a="100" f="b" c="5" x="0" e="0" />
      <i d="2015/8/10" t="" p="31.6" a="200" f="s" c="5" x="6.32" e="0" />
      <i d="2015/8/11" t="" p="31.36" a="100" f="b" c="5" x="0" e="0" />
      <i d="2015/8/13" t="" p="32.15" a="100" f="s" c="5" x="3.22" e="0" />
      <i d="2015/8/14" t="" p="32.23" a="100" f="b" c="5" x="0" e="0" />
      <i d="2015/8/17" t="" p="32.43" a="100" f="s" c="5" x="3.24" e="0" />
      <i d="2015/8/18" t="" p="31.85" a="100" f="b" c="5" x="0" e="0" />
      <i d="2015/8/18" t="" p="31.72" a="100" f="b" c="5" x="0" e="0" />
      <i d="2015/8/18" t="" p="29.33" a="100" f="b" c="5" x="0" e="0" />
      <i d="2015/8/26" t="" p="21.62" a="100" f="b" c="5" x="0" e="0" />
      <i d="2015/8/28" t="" p="22.64" a="100" f="b" c="5" x="0" e="0" />
      <i d="2015/9/1" t="" p="23.65" a="500" f="s" c="5.91" x="11.83" e="0" />
      <i d="2015/9/10" t="" p="25.35" a="500" f="b" c="6.34" x="0" e="0" />
      <i d="2015/9/10" t="" p="24.9" a="500" f="b" c="6.23" x="0" e="0" />
      <i d="2015/9/17" t="" p="21.73" a="400" f="b" c="5" x="0" e="0" />
      <i d="2015/9/17" t="" p="22.94" a="400" f="s" c="5" x="9.18" e="0" />
      <i d="2015/9/22" t="" p="23.74" a="200" f="b" c="5" x="0" e="0" />
      <i d="2015/9/25" t="" p="21.66" a="200" f="b" c="5" x="0" e="0" />
      <i d="2015/9/30" t="" p="22.15" a="200" f="s" c="5" x="4.43" e="0" />
      <i d="2015/9/30" t="" p="22.3" a="200" f="s" c="5" x="4.46" e="0" />
      <i d="2015/9/30" t="" p="23.51" a="500" f="s" c="5.88" x="11.76" e="0" />
      <i d="2015/11/5" t="" p="26.508" a="500" f="s" c="6.63" x="13.25" e="0" />
      <i d="2015/11/25" t="" p="34.31" a="100" f="b" c="5" x="0" e="0" />
      <i d="2015/11/26" t="" p="33.15" a="100" f="b" c="5" x="0" e="0" />
      <i d="2016/2/29" t="" p="23.58" a="200" f="b" c="5" x="0" e="0" />
      <i d="2016/3/1" t="" p="24.32" a="200" f="s" c="5" x="4.86" e="0" />
      <i d="2016/3/11" t="" p="22.2" a="200" f="b" c="5" x="0" e="0" />
      <i d="2016/3/15" t="" p="24.2" a="200" f="s" c="5" x="4.84" e="0" />
      <i d="2016/3/18" t="" p="26.22" a="200" f="s" c="5" x="5.24" e="0" />
      <i d="2016/3/31" t="" p="26.28" a="100" f="b" c="5" x="0" e="0" />
      <i d="2016/3/31" t="" p="25.85" a="100" f="b" c="5" x="0" e="0" />
      <i d="2016/3/31" t="" p="25.65" a="100" f="b" c="5" x="0" e="0" />
      <i d="2016/4/1" t="" p="25.4" a="100" f="b" c="5" x="0" e="0" />
      <i d="2016/4/6" t="" p="26.99" a="400" f="s" c="5.4" x="10.8" e="0" />
      <i d="2016/4/13" t="" p="27.125" a="400" f="b" c="5.43" x="0" e="0" />
      <i d="2016/4/14" t="" p="27.35" a="400" f="s" c="5.47" x="10.94" e="0" />
      <i d="2016/5/25" t="" p="26.85" a="100" f="b" c="5" x="0" e="0" />
      <i d="2016/5/25" t="" p="26.7" a="100" f="b" c="5" x="0" e="0" />
      <i d="2016/6/2" t="" p="27.45" a="200" f="s" c="5" x="5.49" e="0" />
      <i d="2016/11/24" t="" p="28.1" a="100" f="b" c="5" x="0" e="0" />
      <i d="2016/12/9" t="" p="27.2" a="100" f="b" c="5" x="0" e="0" />
      <i d="2017/2/16" t="" p="30" a="200" f="s" c="5" x="6" e="0" />
      <i d="2017/3/21" t="" p="32.99" a="100" f="s" c="5" x="3.3" e="0" />
      <i d="2017/9/7" t="" p="21.4" a="300" f="b" c="5" x="0" e="0" />
      <i d="2017/9/22" t="" p="20.15" a="200" f="b" c="5" x="0" e="0" />
      <i d="2017/10/26" t="" p="21.93" a="500" f="s" c="5.48" x="10.97" e="0" />
      <i d="2017/12/7" t="" p="18" a="500" f="b" c="5" x="0" e="0" />
      <i d="2017/12/8" t="" p="18.32" a="500" f="s" c="5" x="9.16" e="0" />
      <i d="2018/2/6" t="" p="13.22" a="500" f="b" c="5" x="0" e="0" />
      <i d="2018/2/9" t="" p="12.95" a="500" f="b" c="5" x="0" e="0" />
      <i d="2018/2/26" t="" p="14.7" a="500" f="s" c="5" x="7.35" e="0" />
    </recs>
    <advise />
  </stock>
  <stock id="sz002587" symbol="">
    <recs>
      <i d="2015/8/14" t="" p="11.94" a="100" f="b" c="5" x="0" e="0" />
      <i d="2015/8/18" t="" p="11.92" a="100" f="b" c="5" x="0" e="0" />
      <i d="2015/8/18" t="" p="11.91" a="100" f="b" c="5" x="0" e="0" />
      <i d="2015/8/26" t="" p="8.3" a="200" f="b" c="5" x="0" e="0" />
      <i d="2015/8/27" t="" p="8.3" a="400" f="s" c="5" x="3.32" e="0" />
      <i d="2015/8/28" t="" p="8.89" a="500" f="b" c="5" x="0" e="0" />
      <i d="2015/8/31" t="" p="8.57" a="500" f="b" c="5" x="0" e="0" />
      <i d="2015/9/1" t="" p="7.74" a="400" f="b" c="5" x="0" e="0" />
      <i d="2015/9/8" t="" p="7.85" a="500" f="s" c="5" x="3.93" e="0" />
      <i d="2015/9/9" t="" p="8.45" a="1000" f="b" c="5" x="0" e="0" />
      <i d="2015/9/30" t="" p="7.05" a="900" f="s" c="5" x="6.35" e="0" />
      <i d="2015/10/8" t="" p="7.37" a="500" f="b" c="5" x="0" e="0" />
      <i d="2015/10/9" t="" p="7.76" a="500" f="s" c="5" x="3.88" e="0" />
      <i d="2015/10/13" t="" p="9" a="500" f="s" c="5" x="4.5" e="0" />
      <i d="2015/10/15" t="" p="9.3" a="500" f="s" c="5" x="4.65" e="0" />
      <i d="2015/10/27" t="" p="11.25" a="400" f="b" c="5" x="0" e="0" />
      <i d="2015/10/28" t="" p="10.9" a="500" f="b" c="5" x="0" e="0" />
      <i d="2015/11/4" t="" p="11.19" a="500" f="s" c="5" x="5.6" e="0" />
      <i d="2015/11/5" t="" p="11.046" a="500" f="b" c="5" x="0" e="0" />
      <i d="2015/11/10" t="" p="13.16" a="1000" f="s" c="6.58" x="13.16" e="0" />
    </recs>
    <advise />
  </stock>
  <stock id="sh600268" symbol="">
    <recs>
      <i d="2015/9/7" t="" p="7.298" a="500" f="b" c="5" x="0.07" e="0" />
      <i d="2015/9/8" t="" p="7.45" a="500" f="s" c="5" x="3.8" e="0" />
      <i d="2015/9/10" t="" p="8" a="500" f="b" c="5" x="0.08" e="0" />
      <i d="2015/9/30" t="" p="7.45" a="400" f="s" c="5" x="3.04" e="0" />
      <i d="2015/10/12" t="" p="9.28" a="100" f="b" c="5" x="0.02" e="0" />
      <i d="2015/10/12" t="" p="8.99" a="200" f="b" c="5" x="0.04" e="0" />
      <i d="2015/10/13" t="" p="9.6" a="400" f="s" c="5" x="3.92" e="0" />
    </recs>
    <advise />
  </stock>
  <stock id="sh600129" symbol="">
    <recs>
      <i d="2015/9/9" t="" p="17.35" a="500" f="b" c="5" x="0.17" e="0" />
      <i d="2015/9/30" t="" p="15.85" a="400" f="s" c="5" x="6.47" e="0" />
      <i d="2015/10/12" t="" p="17.55" a="100" f="b" c="5" x="0.04" e="0" />
      <i d="2015/10/12" t="" p="18.35" a="100" f="s" c="5" x="1.88" e="0" />
      <i d="2015/10/26" t="" p="20.89" a="100" f="b" c="5" x="0.04" e="0" />
      <i d="2015/10/26" t="" p="20.45" a="200" f="b" c="5" x="0.08" e="0" />
      <i d="2015/11/4" t="" p="22" a="400" f="s" c="5" x="8.98" e="0" />
    </recs>
    <advise />
  </stock>
  <stock id="sz002566" symbol="">
    <recs>
      <i d="2015/9/9" t="" p="15.75" a="500" f="b" c="5" x="0" e="0" />
      <i d="2015/9/30" t="" p="13.18" a="400" f="s" c="5" x="5.27" e="0" />
      <i d="2015/10/12" t="" p="14.19" a="100" f="b" c="5" x="0" e="0" />
      <i d="2015/10/13" t="" p="14.78" a="100" f="s" c="5" x="1.48" e="0" />
      <i d="2015/10/27" t="" p="15.6" a="400" f="b" c="5" x="0" e="0" />
      <i d="2015/11/4" t="" p="16.1" a="400" f="s" c="5" x="6.44" e="0" />
      <i d="2015/11/5" t="" p="16.1" a="100" f="b" c="5" x="0" e="0" />
      <i d="2015/11/19" t="" p="17.04" a="100" f="s" c="5" x="1.7" e="0" />
      <i d="2016/3/15" t="" p="11.33" a="400" f="b" c="5" x="0" e="0" />
      <i d="2016/3/17" t="" p="11.59" a="400" f="s" c="5" x="4.64" e="0" />
      <i d="2017/10/30" t="" p="10.22" a="400" f="b" c="5" x="0" e="0" />
      <i d="2018/2/5" t="" p="7.93" a="500" f="b" c="5" x="0" e="0" />
      <i d="2018/3/6" t="" p="8.12" a="500" f="s" c="5" x="4.06" e="0" />
    </recs>
    <advise />
  </stock>
  <stock id="sh600508" symbol="">
    <recs>
      <i d="2015/9/10" t="" p="9.8" a="500" f="b" c="5" x="0.1" e="0" />
      <i d="2015/9/21" t="" p="10.2" a="500" f="s" c="5" x="5.2" e="0" />
    </recs>
    <advise />
  </stock>
  <stock id="sz002334" symbol="">
    <recs>
      <i d="2015/9/10" t="" p="9.1" a="500" f="b" c="5" x="0" e="0" />
      <i d="2015/9/30" t="" p="8.11" a="400" f="s" c="5" x="3.24" e="0" />
      <i d="2015/10/12" t="" p="9.32" a="100" f="b" c="5" x="0" e="0" />
      <i d="2015/10/15" t="" p="10.25" a="300" f="b" c="5" x="0" e="0" />
      <i d="2015/11/4" t="" p="10.51" a="400" f="s" c="5" x="4.2" e="0" />
      <i d="2015/11/5" t="" p="10.74" a="100" f="b" c="5" x="0" e="0" />
      <i d="2015/11/10" t="" p="10.77" a="200" f="b" c="5" x="0" e="0" />
      <i d="2015/11/11" t="" p="11.2" a="400" f="s" c="5" x="4.48" e="0" />
    </recs>
    <advise />
  </stock>
  <stock id="sh600963" symbol="">
    <recs>
      <i d="2015/9/11" t="" p="7.88" a="100" f="b" c="5" x="0.02" e="0" />
      <i d="2015/9/30" t="" p="6.75" a="100" f="s" c="5" x="0.69" e="0" />
    </recs>
    <advise />
  </stock>
  <stock id="sh600816" symbol="">
    <recs>
      <i d="2015/10/8" t="" p="15.05" a="100" f="b" c="5" x="0.03" e="0" />
      <i d="2015/10/13" t="" p="16.39" a="100" f="s" c="5" x="1.67" e="0" />
    </recs>
    <advise />
  </stock>
  <stock id="sh600187" symbol="">
    <recs>
      <i d="2015/10/12" t="" p="5.27" a="1000" f="b" c="5" x="0.11" e="0" />
      <i d="2015/10/13" t="" p="5.67" a="1000" f="s" c="5" x="5.78" e="0" />
    </recs>
    <advise />
  </stock>
  <stock id="sh600125" symbol="">
    <recs>
      <i d="2015/10/12" t="" p="9.32" a="500" f="b" c="5" x="0.09" e="0" />
      <i d="2015/10/15" t="" p="9.78" a="500" f="s" c="5" x="4.99" e="0" />
    </recs>
    <advise />
  </stock>
  <stock id="sh603030" symbol="">
    <recs>
      <i d="2015/10/14" t="" p="25.75" a="500" f="b" c="6.44" x="0.26" e="0" />
      <i d="2015/10/16" t="" p="26.6" a="500" f="s" c="6.65" x="13.57" e="0" />
    </recs>
    <advise />
  </stock>
  <stock id="sz000001" symbol="">
    <recs>
      <i d="2015/10/15" t="" p="11" a="500" f="b" c="5" x="0" e="0" />
      <i d="2015/10/23" t="" p="11.5" a="500" f="s" c="5" x="5.75" e="0" />
    </recs>
    <advise />
  </stock>
  <stock id="sh601678" symbol="">
    <recs>
      <i d="2015/10/16" t="" p="7.71" a="500" f="b" c="5" x="0.08" e="0" />
      <i d="2015/11/4" t="" p="7.9" a="500" f="s" c="5" x="4.03" e="0" />
    </recs>
    <advise />
  </stock>
  <stock id="sh600086" symbol="">
    <recs>
      <i d="2015/10/26" t="" p="13.82" a="500" f="b" c="5" x="0.14" e="0" />
      <i d="2015/10/26" t="" p="13.35" a="500" f="b" c="5" x="0.13" e="0" />
      <i d="2015/11/2" t="" p="11.7" a="500" f="b" c="5" x="0.12" e="0" />
      <i d="2015/11/5" t="" p="11.83" a="500" f="b" c="5" x="0.12" e="0" />
      <i d="2015/11/12" t="" p="12.8" a="2000" f="s" c="12.8" x="26.11" e="0" />
    </recs>
    <advise />
  </stock>
  <stock id="sh600527" symbol="">
    <recs>
      <i d="2015/10/28" t="" p="6.65" a="1000" f="b" c="5" x="0.13" e="0" />
      <i d="2015/10/30" t="" p="7.35" a="1000" f="s" c="5" x="7.5" e="0" />
    </recs>
    <advise />
  </stock>
  <stock id="sz002218" symbol="">
    <recs>
      <i d="2015/11/3" t="" p="9.8" a="300" f="b" c="5" x="0" e="0" />
      <i d="2015/11/4" t="" p="10.2" a="300" f="s" c="5" x="3.06" e="0" />
      <i d="2015/11/10" t="" p="10.29" a="500" f="b" c="5" x="0" e="0" />
      <i d="2015/11/11" t="" p="10.6" a="500" f="s" c="5" x="5.3" e="0" />
    </recs>
    <advise />
  </stock>
  <stock id="sh601368" symbol="">
    <recs>
      <i d="2015/11/4" t="" p="19.3" a="500" f="b" c="5" x="0.19" e="0" />
      <i d="2015/11/5" t="" p="19.71" a="500" f="s" c="5" x="10.05" e="0" />
      <i d="2015/11/6" t="" p="20.75" a="500" f="b" c="5.19" x="0.21" e="0" />
      <i d="2015/11/10" t="" p="19.91" a="500" f="b" c="5" x="0.2" e="0" />
      <i d="2015/11/12" t="" p="20.99" a="1000" f="s" c="10.5" x="21.41" e="0" />
    </recs>
    <advise />
  </stock>
  <stock id="sh600095" symbol="">
    <recs>
      <i d="2015/11/4" t="" p="12.24" a="500" f="b" c="5" x="0.12" e="0" />
      <i d="2015/11/5" t="" p="12.1" a="500" f="b" c="5" x="0.12" e="0" />
      <i d="2016/2/26" t="" p="8.66" a="500" f="s" c="5" x="4.42" e="0" />
      <i d="2016/3/7" t="" p="8.83" a="400" f="s" c="5" x="3.61" e="0" />
      <i d="2016/3/15" t="" p="8.08" a="400" f="b" c="5" x="0.06" e="0" />
      <i d="2016/3/17" t="" p="8.28" a="400" f="s" c="5" x="3.38" e="0" />
      <i d="2017/9/6" t="" p="8.17" a="400" f="b" c="5" x="0.06" e="0" />
      <i d="2017/10/24" t="" p="7.68" a="100" f="b" c="5" x="0.02" e="0" />
      <i d="2017/10/27" t="" p="7.34" a="400" f="b" c="5" x="0.06" e="0" />
    </recs>
    <advise />
  </stock>
  <stock id="sh603117" symbol="">
    <recs>
      <i d="2015/11/9" t="" p="29.75" a="400" f="b" c="5.95" x="0.24" e="0" />
      <i d="2015/11/12" t="" p="33.39" a="400" f="s" c="6.68" x="13.63" e="0" />
    </recs>
    <advise />
  </stock>
  <stock id="sh601599" symbol="">
    <recs>
      <i d="2015/11/11" t="" p="27.1" a="200" f="b" c="5" x="0.11" e="0" />
      <i d="2015/11/12" t="" p="26.43" a="200" f="b" c="5" x="0.11" e="0" />
      <i d="2015/11/13" t="" p="25.51" a="400" f="b" c="5.1" x="0.2" e="0" />
      <i d="2015/11/24" t="" p="23.73" a="200" f="b" c="5" x="0.09" e="0" />
      <i d="2016/2/26" t="" p="18.15" a="500" f="s" c="5" x="9.26" e="0" />
      <i d="2016/3/18" t="" p="19.27" a="400" f="s" c="5" x="7.86" e="0" />
      <i d="2016/8/5" t="" p="12.25" a="200" f="b" c="5" x="0.05" e="0" />
      <i d="2016/8/8" t="" p="11" a="400" f="b" c="5" x="0.09" e="0" />
      <i d="2016/11/7" t="" p="10.34" a="300" f="s" c="5" x="3.16" e="0" />
      <i d="2018/2/5" t="" p="5.97" a="500" f="b" c="5" x="0.06" e="0" />
      <i d="2018/3/6" t="" p="6.05" a="500" f="s" c="5" x="3.09" e="0" />
    </recs>
    <advise />
  </stock>
  <stock id="sh601069" symbol="">
    <recs>
      <i d="2015/11/11" t="" p="20.23" a="500" f="b" c="5.06" x="0.2" e="0" />
      <i d="2015/11/12" t="" p="20.44" a="500" f="s" c="5.11" x="10.42" e="0" />
    </recs>
    <advise />
  </stock>
  <stock id="sz002723" symbol="">
    <recs>
      <i d="2015/11/12" t="" p="28.88" a="500" f="b" c="7.22" x="0" e="0" />
      <i d="2015/11/13" t="" p="27.518" a="500" f="b" c="6.88" x="0" e="0" />
      <i d="2015/11/19" t="" p="24.42" a="500" f="b" c="6.11" x="0" e="0" />
      <i d="2015/11/19" t="" p="25.34" a="500" f="s" c="6.34" x="12.67" e="0" />
      <i d="2016/3/11" t="" p="16.05" a="500" f="s" c="5" x="8.03" e="0" />
      <i d="2016/3/16" t="" p="18.37" a="400" f="s" c="5" x="7.35" e="0" />
      <i d="2016/6/15" t="" p="25.06" a="100" f="s" c="5" x="2.51" e="0" />
    </recs>
    <advise />
  </stock>
  <stock id="sz000622" symbol="">
    <recs>
      <i d="2015/11/18" t="" p="14.14" a="500" f="b" c="5" x="0" e="0" />
      <i d="2015/11/20" t="" p="14.8" a="500" f="s" c="5" x="7.4" e="0" />
    </recs>
    <advise />
  </stock>
  <stock id="sz000517" symbol="">
    <recs>
      <i d="2015/11/20" t="" p="5.97" a="1000" f="b" c="5" x="0" e="0" />
      <i d="2015/11/23" t="" p="6.22" a="1000" f="s" c="5" x="6.22" e="0" />
    </recs>
    <advise />
  </stock>
  <stock id="sz000701" symbol="">
    <recs>
      <i d="2016/2/29" t="" p="15.4" a="200" f="b" c="5" x="0" e="0" />
      <i d="2016/3/1" t="" p="16.13" a="200" f="s" c="5" x="3.23" e="0" />
    </recs>
    <advise />
  </stock>
  <stock id="sz002745" symbol="">
    <recs>
      <i d="2016/3/2" t="" p="27.1" a="200" f="b" c="5" x="0" e="0" />
      <i d="2016/3/3" t="" p="27.85" a="200" f="s" c="5" x="5.57" e="0" />
    </recs>
    <advise />
  </stock>
  <stock id="sz002285" symbol="">
    <recs>
      <i d="2016/3/3" t="" p="15.51" a="200" f="b" c="5" x="0" e="0" />
      <i d="2016/3/3" t="" p="15.06" a="200" f="b" c="5" x="0" e="0" />
      <i d="2016/3/8" t="" p="13" a="200" f="b" c="5" x="0" e="0" />
      <i d="2016/3/8" t="" p="12.88" a="200" f="b" c="5" x="0" e="0" />
      <i d="2016/3/8" t="" p="13.62" a="400" f="s" c="5" x="5.44" e="0" />
      <i d="2016/3/11" t="" p="12.72" a="200" f="b" c="5" x="0" e="0" />
      <i d="2016/3/11" t="" p="12.59" a="200" f="s" c="5" x="2.52" e="0" />
      <i d="2016/3/14" t="" p="12.75" a="100" f="b" c="5" x="0" e="0" />
      <i d="2016/3/16" t="" p="12.42" a="200" f="b" c="5" x="0" e="0" />
      <i d="2016/3/17" t="" p="12.73" a="300" f="s" c="5" x="3.82" e="0" />
      <i d="2016/3/18" t="" p="13.35" a="300" f="s" c="5" x="4.01" e="0" />
      <i d="2016/3/31" t="" p="13.2" a="100" f="b" c="5" x="0" e="0" />
      <i d="2016/3/31" t="" p="13.18" a="100" f="b" c="5" x="0" e="0" />
      <i d="2016/4/1" t="" p="13" a="200" f="b" c="5" x="0" e="0" />
      <i d="2016/4/7" t="" p="13.81" a="400" f="s" c="5" x="5.52" e="0" />
      <i d="2016/4/14" t="" p="9.7" a="200" f="b" c="5" x="0" e="0" />
      <i d="2016/4/18" t="" p="9.39" a="200" f="b" c="5" x="0" e="0" />
      <i d="2016/4/21" t="" p="8.6" a="200" f="s" c="5" x="1.72" e="0" />
      <i d="2016/4/25" t="" p="8.39" a="200" f="b" c="5" x="0" e="0" />
      <i d="2016/4/26" t="" p="8.54" a="300" f="s" c="5" x="2.56" e="0" />
      <i d="2016/4/28" t="" p="8.38" a="200" f="b" c="5" x="0" e="0" />
      <i d="2016/4/28" t="" p="8.37" a="100" f="b" c="5" x="0" e="0" />
      <i d="2016/4/28" t="" p="8.43" a="240" f="s" c="5" x="2.02" e="0" />
      <i d="2016/5/3" t="" p="8.47" a="300" f="b" c="5" x="0" e="0" />
      <i d="2016/5/13" t="" p="7.8" a="400" f="b" c="5" x="0" e="0" />
      <i d="2016/5/25" t="" p="7.33" a="500" f="b" c="5" x="0" e="0" />
      <i d="2016/5/26" t="" p="7.39" a="500" f="s" c="5" x="3.7" e="0" />
      <i d="2016/6/2" t="" p="7.66" a="500" f="s" c="5" x="3.83" e="0" />
      <i d="2016/7/14" t="" p="8.85" a="400" f="s" c="5" x="3.54" e="0" />
      <i d="2016/11/9" t="" p="7.92" a="400" f="b" c="5" x="0" e="0" />
      <i d="2016/11/23" t="" p="8.41" a="400" f="s" c="5" x="3.36" e="0" />
      <i d="2017/8/29" t="" p="11.8" a="100" f="s" c="5" x="1.18" e="0" />
    </recs>
    <advise />
  </stock>
  <stock id="sz000520" symbol="">
    <recs>
      <i d="2016/3/16" t="" p="9.09" a="300" f="b" c="5" x="0" e="0" />
      <i d="2016/3/17" t="" p="9.56" a="300" f="s" c="5" x="2.87" e="0" />
    </recs>
    <advise />
  </stock>
  <stock id="sz000810" symbol="">
    <recs>
      <i d="2016/3/16" t="" p="12.88" a="200" f="b" c="5" x="0" e="0" />
      <i d="2016/3/17" t="" p="14.14" a="200" f="s" c="5" x="2.83" e="0" />
    </recs>
    <advise />
  </stock>
  <stock id="sh600565" symbol="">
    <recs>
      <i d="2016/3/24" t="" p="7.5" a="500" f="b" c="5" x="0.08" e="0" />
      <i d="2016/4/6" t="" p="7.67" a="500" f="s" c="5" x="3.92" e="0" />
    </recs>
    <advise />
  </stock>
  <stock id="sh600085" symbol="">
    <recs>
      <i d="2016/3/24" t="" p="28.55" a="200" f="b" c="5" x="0.11" e="0" />
      <i d="2016/3/25" t="" p="29.18" a="200" f="s" c="5" x="5.96" e="0" />
      <i d="2016/6/3" t="" p="28.04" a="500" f="b" c="7.01" x="0.28" e="0" />
      <i d="2016/6/6" t="" p="27.71" a="200" f="b" c="5" x="0.11" e="0" />
      <i d="2016/6/15" t="" p="27.12" a="100" f="b" c="5" x="0.05" e="0" />
      <i d="2016/6/21" t="" p="27.55" a="300" f="s" c="5" x="8.44" e="0" />
      <i d="2016/6/28" t="" p="30.04" a="500" f="s" c="7.51" x="15.32" e="0" />
      <i d="2017/8/29" t="" p="32.33" a="500" f="b" c="8.08" x="0.32" e="0" />
      <i d="2017/10/18" t="" p="33.45" a="500" f="s" c="8.36" x="17.06" e="0" />
    </recs>
    <advise />
  </stock>
  <stock id="sz002463" symbol="">
    <recs>
      <i d="2016/3/24" t="" p="4.97" a="500" f="b" c="5" x="0" e="0" />
      <i d="2016/3/29" t="" p="4.57" a="500" f="b" c="5" x="0" e="0" />
      <i d="2016/3/30" t="" p="4.72" a="500" f="s" c="5" x="2.36" e="0" />
      <i d="2016/4/6" t="" p="4.91" a="500" f="s" c="5" x="2.46" e="0" />
    </recs>
    <advise />
  </stock>
  <stock id="sz000519" symbol="">
    <recs>
      <i d="2016/3/24" t="" p="13.85" a="400" f="b" c="5" x="0" e="0" />
      <i d="2016/3/29" t="" p="13.22" a="400" f="b" c="5" x="0" e="0" />
      <i d="2016/3/30" t="" p="13.48" a="300" f="s" c="5" x="4.04" e="0" />
      <i d="2016/4/6" t="" p="13.82" a="500" f="s" c="5" x="6.91" e="0" />
    </recs>
    <advise />
  </stock>
  <stock id="sz000629" symbol="">
    <recs>
      <i d="2016/4/6" t="" p="3.23" a="1000" f="b" c="5" x="0" e="0" />
      <i d="2016/4/7" t="" p="3.14" a="500" f="b" c="5" x="0" e="0" />
      <i d="2016/4/7" t="" p="3.25" a="500" f="s" c="5" x="1.63" e="0" />
      <i d="2016/4/21" t="" p="3.16" a="900" f="s" c="5" x="2.84" e="0" />
      <i d="2016/4/28" t="" p="2.97" a="400" f="b" c="5" x="0" e="0" />
      <i d="2016/5/3" t="" p="2.83" a="400" f="s" c="5" x="1.13" e="0" />
      <i d="2016/12/1" t="" p="2.69" a="400" f="b" c="5" x="0" e="0" />
      <i d="2017/1/4" t="" p="2.39" a="500" f="b" c="5" x="0" e="0" />
      <i d="2017/3/2" t="" p="2.61" a="900" f="s" c="5" x="2.35" e="0" />
      <i d="2017/4/10" t="" p="2.71" a="100" f="s" c="5" x="0.27" e="0" />
    </recs>
    <advise />
  </stock>
  <stock id="sz000627" symbol="">
    <recs>
      <i d="2016/4/6" t="" p="8.1" a="500" f="b" c="5" x="0" e="0" />
      <i d="2016/4/7" t="" p="8.23" a="500" f="s" c="5" x="4.12" e="0" />
    </recs>
    <advise />
  </stock>
  <stock id="sz000066" symbol="">
    <recs>
      <i d="2016/4/12" t="" p="22.69" a="200" f="b" c="5" x="0" e="0" />
      <i d="2016/4/13" t="" p="22.74" a="300" f="b" c="5" x="0" e="0" />
      <i d="2016/4/20" t="" p="20.4" a="200" f="s" c="5" x="4.08" e="0" />
      <i d="2016/4/28" t="" p="19.04" a="200" f="b" c="5" x="0" e="0" />
      <i d="2016/4/28" t="" p="19.25" a="200" f="s" c="5" x="3.85" e="0" />
      <i d="2016/5/3" t="" p="19.75" a="300" f="b" c="5" x="0" e="0" />
      <i d="2016/5/3" t="" p="19.65" a="300" f="b" c="5" x="0" e="0" />
      <i d="2016/5/11" t="" p="17.25" a="600" f="b" c="5.18" x="0" e="0" />
      <i d="2016/5/24" t="" p="16.6" a="500" f="b" c="5" x="0" e="0" />
      <i d="2016/5/24" t="" p="16.98" a="500" f="s" c="5" x="8.49" e="0" />
      <i d="2016/6/2" t="" p="17.75" a="1000" f="s" c="8.88" x="17.75" e="0" />
      <i d="2016/6/27" t="" p="16.89" a="500" f="b" c="5" x="0" e="0" />
      <i d="2016/6/28" t="" p="18.43" a="500" f="s" c="5" x="9.22" e="0" />
      <i d="2017/2/21" t="" p="10.1" a="422" f="s" c="5" x="4.26" e="0" />
      <i d="2017/9/1" t="" p="8.42" a="500" f="b" c="5" x="0" e="0" />
      <i d="2017/9/22" t="" p="8.92" a="500" f="s" c="5" x="4.46" e="0" />
      <i d="2017/10/19" t="" p="8.17" a="500" f="b" c="5" x="0" e="0" />
      <i d="2017/12/14" t="" p="7.11" a="1000" f="b" c="5" x="0" e="0" />
      <i d="2017/12/20" t="" p="6.8" a="1000" f="b" c="5" x="0" e="0" />
      <i d="2017/12/26" t="" p="6.5" a="1000" f="s" c="5" x="6.5" e="0" />
      <i d="2018/1/2" t="" p="7.21" a="1000" f="s" c="5" x="7.21" e="0" />
      <i d="2018/1/17" t="" p="7.04" a="1000" f="s" c="5" x="7.04" e="0" />
    </recs>
    <advise />
  </stock>
  <stock id="sh601958" symbol="">
    <recs>
      <i d="2016/4/15" t="" p="7.96" a="500" f="b" c="5" x="0.08" e="0" />
      <i d="2016/4/21" t="" p="7.55" a="200" f="s" c="5" x="1.54" e="0" />
      <i d="2016/4/21" t="" p="7.85" a="200" f="s" c="5" x="1.6" e="0" />
      <i d="2016/4/27" t="" p="7.59" a="400" f="b" c="5" x="0.06" e="0" />
      <i d="2016/4/28" t="" p="7.53" a="200" f="s" c="5" x="1.54" e="0" />
      <i d="2016/5/3" t="" p="7.79" a="300" f="b" c="5" x="0.05" e="0" />
      <i d="2016/5/11" t="" p="7.17" a="400" f="b" c="5" x="0.06" e="0" />
      <i d="2016/5/13" t="" p="7.55" a="500" f="s" c="5" x="3.86" e="0" />
      <i d="2016/5/24" t="" p="8.29" a="500" f="s" c="5" x="4.23" e="0" />
    </recs>
    <advise />
  </stock>
  <stock id="sz000547" symbol="">
    <recs>
      <i d="2016/4/18" t="" p="15.43" a="97" f="b" c="5" x="0" e="0" />
      <i d="2016/4/18" t="" p="15.47" a="400" f="b" c="5" x="0" e="0" />
    </recs>
    <advise />
  </stock>
  <stock id="sh601918" symbol="">
    <recs>
      <i d="2015/11/5" t="" p="12.25" a="500" f="b" c="5" x="0.12" e="0" />
      <i d="2015/11/13" t="" p="11.79" a="500" f="b" c="5" x="0.12" e="0" />
      <i d="2015/11/23" t="" p="11.34" a="1000" f="b" c="5.67" x="0.22" e="0" />
      <i d="2016/2/26" t="" p="7.15" a="1000" f="s" c="5" x="7.29" e="0" />
      <i d="2016/3/9" t="" p="6.58" a="500" f="b" c="5" x="0.07" e="0" />
      <i d="2016/3/11" t="" p="6.08" a="500" f="s" c="5" x="3.1" e="0" />
      <i d="2016/3/18" t="" p="6.51" a="500" f="s" c="5" x="3.33" e="0" />
      <i d="2016/3/29" t="" p="6.2" a="500" f="b" c="5" x="0.06" e="0" />
      <i d="2016/4/5" t="" p="6.93" a="500" f="s" c="5" x="3.54" e="0" />
      <i d="2016/4/6" t="" p="6.68" a="500" f="b" c="5" x="0.07" e="0" />
      <i d="2016/4/7" t="" p="6.45" a="500" f="b" c="5" x="0.06" e="0" />
      <i d="2016/4/14" t="" p="6.94" a="500" f="s" c="5" x="3.54" e="0" />
      <i d="2016/4/20" t="" p="6.18" a="500" f="s" c="5" x="3.15" e="0" />
      <i d="2016/4/28" t="" p="5.88" a="500" f="b" c="5" x="0.06" e="0" />
      <i d="2016/5/5" t="" p="5.06" a="900" f="s" c="5" x="4.64" e="0" />
      <i d="2017/8/28" t="" p="4.66" a="400" f="b" c="5" x="0.04" e="0" />
      <i d="2017/8/29" t="" p="4.65" a="500" f="b" c="5" x="0.05" e="0" />
      <i d="2017/9/6" t="" p="5.05" a="500" f="s" c="5" x="2.58" e="0" />
      <i d="2017/10/18" t="" p="4.28" a="500" f="b" c="5" x="0.04" e="0" />
      <i d="2017/11/17" t="" p="3.89" a="400" f="b" c="5" x="0.03" e="0" />
      <i d="2018/1/31" t="" p="3.58" a="600" f="b" c="5" x="0.04" e="0" />
    </recs>
    <advise />
  </stock>
  <stock id="sh600429" symbol="">
    <recs>
      <i d="2016/6/1" t="" p="8.34" a="500" f="b" c="5" x="0.08" e="0" />
      <i d="2016/6/2" t="" p="8.55" a="500" f="s" c="5" x="4.37" e="0" />
    </recs>
    <advise />
  </stock>
  <stock id="sz002276" symbol="">
    <recs>
      <i d="2016/6/3" t="" p="19.63" a="500" f="b" c="5" x="0" e="0" />
      <i d="2016/6/13" t="" p="18.37" a="300" f="b" c="5" x="0" e="0" />
      <i d="2016/6/15" t="" p="20.18" a="300" f="s" c="5" x="6.05" e="0" />
      <i d="2016/7/12" t="" p="20.03" a="500" f="s" c="5.01" x="10.02" e="0" />
    </recs>
    <advise />
  </stock>
  <stock id="sz300030" symbol="">
    <recs>
      <i d="2016/6/23" t="" p="15.21" a="500" f="b" c="5" x="0" e="0" />
      <i d="2016/6/24" t="" p="15.4" a="500" f="s" c="5" x="7.7" e="0" />
    </recs>
    <advise />
  </stock>
  <stock id="sh600416" symbol="">
    <recs>
      <i d="2016/6/30" t="" p="12.27" a="500" f="b" c="5" x="0.12" e="0" />
      <i d="2016/7/5" t="" p="13.3" a="500" f="s" c="5" x="6.78" e="0" />
    </recs>
    <advise />
  </stock>
  <stock id="sz300059" symbol="">
    <recs>
      <i d="2016/6/30" t="" p="22.25" a="500" f="b" c="5.56" x="0" e="0" />
      <i d="2016/7/15" t="" p="21.94" a="500" f="b" c="5.49" x="0" e="0" />
      <i d="2016/7/15" t="" p="21.2" a="500" f="b" c="5.3" x="0" e="0" />
      <i d="2016/11/11" t="" p="20.1" a="500" f="s" c="5.03" x="10.05" e="0" />
      <i d="2016/11/24" t="" p="21.1" a="500" f="s" c="5.28" x="10.55" e="0" />
      <i d="2016/12/23" t="" p="17.85" a="500" f="b" c="5" x="0" e="0" />
      <i d="2016/12/23" t="" p="17.3" a="300" f="b" c="5" x="0" e="0" />
      <i d="2016/12/26" t="" p="16.73" a="100" f="b" c="5" x="0" e="0" />
      <i d="2017/1/13" t="" p="16.45" a="100" f="b" c="5" x="0" e="0" />
      <i d="2017/8/8" t="" p="13.3" a="300" f="s" c="5" x="3.99" e="0" />
      <i d="2017/8/28" t="" p="15.1" a="500" f="s" c="5" x="7.55" e="0" />
      <i d="2017/11/29" t="" p="13.82" a="500" f="s" c="5" x="6.91" e="0" />
      <i d="2017/12/6" t="" p="14.05" a="500" f="s" c="5" x="7.03" e="0" />
    </recs>
    <advise />
  </stock>
  <stock id="sz300352" symbol="">
    <recs>
      <i d="2016/7/5" t="" p="18.7" a="500" f="b" c="5" x="0" e="0" />
      <i d="2016/7/12" t="" p="20.13" a="500" f="s" c="5.03" x="10.07" e="0" />
    </recs>
    <advise />
  </stock>
  <stock id="sh600446" symbol="">
    <recs>
      <i d="2016/7/11" t="" p="35.33" a="300" f="b" c="5.3" x="0.22" e="0" />
      <i d="2016/7/12" t="" p="35.75" a="300" f="s" c="5.36" x="10.94" e="0" />
    </recs>
    <advise />
  </stock>
  <stock id="sz300209" symbol="">
    <recs>
      <i d="2016/7/13" t="" p="26.5" a="500" f="b" c="6.63" x="0" e="0" />
      <i d="2016/7/14" t="" p="26.952" a="500" f="s" c="6.74" x="13.48" e="0" />
    </recs>
    <advise />
  </stock>
  <stock id="sh600399" symbol="">
    <recs>
      <i d="2016/7/15" t="" p="7.64" a="500" f="b" c="5" x="0.08" e="0" />
      <i d="2016/8/3" t="" p="6.8" a="500" f="b" c="5" x="0.07" e="0" />
      <i d="2016/10/24" t="" p="7.48" a="500" f="s" c="5" x="3.81" e="0" />
      <i d="2016/11/11" t="" p="8.13" a="500" f="s" c="5" x="4.15" e="0" />
    </recs>
    <advise />
  </stock>
  <stock id="sz000021" symbol="">
    <recs>
      <i d="2016/11/14" t="" p="10.74" a="500" f="b" c="5" x="0" e="0" />
      <i d="2016/11/24" t="" p="10.75" a="500" f="s" c="5" x="5.38" e="0" />
    </recs>
    <advise />
  </stock>
  <stock id="sh603996" symbol="">
    <recs>
      <i d="2016/11/23" t="" p="27.07" a="100" f="b" c="5" x="0.05" e="0" />
      <i d="2016/11/23" t="" p="26.65" a="100" f="b" c="5" x="0.05" e="0" />
      <i d="2016/11/25" t="" p="25.86" a="100" f="b" c="5" x="0.05" e="0" />
      <i d="2016/11/25" t="" p="26.41" a="100" f="s" c="5" x="2.69" e="0" />
      <i d="2016/11/29" t="" p="25.9" a="100" f="b" c="5" x="0.05" e="0" />
      <i d="2016/12/1" t="" p="24.72" a="300" f="s" c="5" x="7.56" e="0" />
    </recs>
    <advise />
  </stock>
  <stock id="sh600118" symbol="">
    <recs>
      <i d="2016/11/23" t="" p="32.37" a="100" f="b" c="5" x="0.06" e="0" />
      <i d="2016/11/24" t="" p="33.2" a="100" f="b" c="5" x="0.07" e="0" />
      <i d="2016/11/25" t="" p="33.54" a="100" f="s" c="5" x="3.42" e="0" />
      <i d="2018/2/5" t="" p="22" a="200" f="b" c="5" x="0.09" e="0" />
      <i d="2018/2/9" t="" p="19.05" a="100" f="b" c="5" x="0.04" e="0" />
      <i d="2018/2/9" t="" p="18.85" a="100" f="b" c="5" x="0.04" e="0" />
      <i d="2018/3/12" t="" p="22.11" a="200" f="s" c="5" x="4.51" e="0" />
    </recs>
    <advise />
  </stock>
  <stock id="sz300242" symbol="">
    <recs>
      <i d="2016/11/23" t="" p="16.7" a="100" f="b" c="5" x="0" e="0" />
      <i d="2016/11/24" t="" p="17.3" a="100" f="s" c="5" x="1.73" e="0" />
    </recs>
    <advise />
  </stock>
  <stock id="sz300043" symbol="">
    <recs>
      <i d="2016/11/23" t="" p="12.54" a="100" f="b" c="5" x="0" e="0" />
      <i d="2016/11/24" t="" p="12.4" a="100" f="b" c="5" x="0" e="0" />
      <i d="2016/11/25" t="" p="12.13" a="100" f="b" c="5" x="0" e="0" />
      <i d="2016/11/25" t="" p="12.03" a="200" f="b" c="5" x="0" e="0" />
      <i d="2016/11/25" t="" p="11.8" a="200" f="b" c="5" x="0" e="0" />
      <i d="2016/11/28" t="" p="11.97" a="300" f="b" c="5" x="0" e="0" />
      <i d="2016/12/5" t="" p="11.69" a="200" f="b" c="5" x="0" e="0" />
      <i d="2017/2/24" t="" p="10.2" a="200" f="s" c="5" x="2.04" e="0" />
      <i d="2018/2/8" t="" p="5.49" a="200" f="s" c="5" x="1.1" e="0" />
      <i d="2018/2/28" t="" p="5.42" a="300" f="s" c="5" x="1.63" e="0" />
    </recs>
    <advise />
  </stock>
  <stock id="sz300465" symbol="">
    <recs>
      <i d="2016/11/23" t="" p="22.8" a="100" f="b" c="5" x="0" e="0" />
      <i d="2016/11/25" t="" p="21.65" a="100" f="b" c="5" x="0" e="0" />
      <i d="2016/11/25" t="" p="21.55" a="100" f="b" c="5" x="0" e="0" />
      <i d="2016/11/25" t="" p="20.6" a="100" f="b" c="5" x="0" e="0" />
      <i d="2016/11/25" t="" p="21.3" a="100" f="s" c="5" x="2.13" e="0" />
      <i d="2016/11/29" t="" p="21.03" a="100" f="b" c="5" x="0" e="0" />
      <i d="2016/12/5" t="" p="22.38" a="100" f="s" c="5" x="2.24" e="0" />
      <i d="2016/12/5" t="" p="22.3" a="100" f="s" c="5" x="2.23" e="0" />
      <i d="2016/12/7" t="" p="21.6" a="200" f="b" c="5" x="0" e="0" />
      <i d="2016/12/8" t="" p="20.95" a="100" f="b" c="5" x="0" e="0" />
      <i d="2016/12/12" t="" p="19.99" a="100" f="b" c="5" x="0" e="0" />
      <i d="2016/12/30" t="" p="18.2" a="100" f="s" c="5" x="1.82" e="0" />
      <i d="2016/12/30" t="" p="18.2" a="400" f="s" c="5" x="7.28" e="0" />
      <i d="2017/2/22" t="" p="14.68" a="400" f="b" c="5" x="0" e="0" />
      <i d="2017/2/23" t="" p="14.48" a="300" f="b" c="5" x="0" e="0" />
      <i d="2017/2/23" t="" p="14.67" a="300" f="s" c="5" x="4.4" e="0" />
      <i d="2017/3/1" t="" p="15.35" a="400" f="s" c="5" x="6.14" e="0" />
      <i d="2017/3/9" t="" p="15.05" a="100" f="b" c="5" x="0" e="0" />
      <i d="2017/3/21" t="" p="14.68" a="200" f="b" c="5" x="0" e="0" />
      <i d="2017/8/31" t="" p="11.05" a="200" f="s" c="5" x="2.21" e="0" />
      <i d="2017/9/7" t="" p="11.81" a="200" f="b" c="5" x="0" e="0" />
      <i d="2017/9/7" t="" p="12.78" a="200" f="s" c="5" x="2.56" e="0" />
      <i d="2017/10/19" t="" p="9.86" a="300" f="b" c="5" x="0" e="0" />
      <i d="2017/12/19" t="" p="9.98" a="300" f="s" c="5" x="2.99" e="0" />
      <i d="2017/12/26" t="" p="9.38" a="200" f="s" c="5" x="1.88" e="0" />
    </recs>
    <advise />
  </stock>
  <stock id="sz002546" symbol="">
    <recs>
      <i d="2016/11/24" t="" p="10.3" a="500" f="b" c="5" x="0" e="0" />
      <i d="2016/11/28" t="" p="10.21" a="500" f="b" c="5" x="0" e="0" />
      <i d="2017/10/18" t="" p="6" a="1000" f="b" c="5" x="0" e="0" />
      <i d="2017/11/17" t="" p="5.41" a="1000" f="b" c="5" x="0" e="0" />
      <i d="2018/1/11" t="" p="5.11" a="1000" f="s" c="5" x="5.11" e="0" />
      <i d="2018/1/15" t="" p="5" a="500" f="b" c="5" x="0" e="0" />
      <i d="2018/1/31" t="" p="4.85" a="500" f="b" c="5" x="0" e="0" />
      <i d="2018/2/1" t="" p="4.4" a="500" f="b" c="5" x="0" e="0" />
      <i d="2018/3/6" t="" p="4.53" a="500" f="s" c="5" x="2.27" e="0" />
    </recs>
    <advise />
  </stock>
  <stock id="sz300079" symbol="">
    <recs>
      <i d="2016/12/1" t="" p="8.34" a="200" f="b" c="5" x="0" e="0" />
      <i d="2016/12/2" t="" p="8.16" a="200" f="b" c="5" x="0" e="0" />
      <i d="2016/12/5" t="" p="8.11" a="100" f="b" c="5" x="0" e="0" />
      <i d="2016/12/30" t="" p="7.24" a="200" f="b" c="5" x="0" e="0" />
      <i d="2017/1/5" t="" p="7.35" a="200" f="s" c="5" x="1.47" e="0" />
      <i d="2017/5/2" t="" p="6.16" a="100" f="b" c="5" x="0" e="0" />
      <i d="2017/10/19" t="" p="5.29" a="400" f="b" c="5" x="0" e="0" />
      <i d="2018/2/5" t="" p="3.53" a="500" f="b" c="5" x="0" e="0" />
      <i d="2018/2/5" t="" p="3.55" a="500" f="b" c="5" x="0" e="0" />
      <i d="2018/3/6" t="" p="3.78" a="1000" f="s" c="5" x="3.78" e="0" />
    </recs>
    <advise />
  </stock>
  <stock id="sz300418" symbol="">
    <recs>
      <i d="2016/12/1" t="" p="26.51" a="100" f="b" c="5" x="0" e="0" />
      <i d="2016/12/2" t="" p="26" a="100" f="b" c="5" x="0" e="0" />
      <i d="2017/2/27" t="" p="22.9" a="200" f="b" c="5" x="0" e="0" />
      <i d="2017/3/3" t="" p="21.55" a="100" f="b" c="5" x="0" e="0" />
      <i d="2017/3/7" t="" p="22.41" a="100" f="s" c="5" x="2.24" e="0" />
      <i d="2017/3/30" t="" p="21" a="100" f="b" c="5" x="0" e="0" />
      <i d="2017/8/28" t="" p="26.28" a="500" f="s" c="6.57" x="13.14" e="0" />
    </recs>
    <advise />
  </stock>
  <stock id="sz300058" symbol="">
    <recs>
      <i d="2017/1/23" t="" p="9.55" a="500" f="b" c="5" x="0" e="0" />
      <i d="2017/2/24" t="" p="10.17" a="300" f="s" c="5" x="3.05" e="0" />
      <i d="2017/3/27" t="" p="9.38" a="300" f="b" c="5" x="0" e="0" />
      <i d="2017/3/30" t="" p="9.1" a="500" f="b" c="5" x="0" e="0" />
      <i d="2017/4/10" t="" p="8.91" a="100" f="b" c="5" x="0" e="0" />
      <i d="2017/9/6" t="" p="7.97" a="100" f="s" c="5" x="0.8" e="0" />
      <i d="2018/1/17" t="" p="5.92" a="1000" f="s" c="5" x="5.92" e="0" />
    </recs>
    <advise />
  </stock>
  <stock id="sz300220" symbol="">
    <recs>
      <i d="2017/2/24" t="" p="28" a="200" f="b" c="5" x="0" e="0" />
      <i d="2017/2/27" t="" p="29" a="200" f="s" c="5" x="5.8" e="0" />
      <i d="2017/3/1" t="" p="27.72" a="200" f="b" c="5" x="0" e="0" />
      <i d="2017/3/6" t="" p="28.52" a="200" f="s" c="5" x="5.7" e="0" />
      <i d="2017/3/8" t="" p="28.5" a="200" f="b" c="5" x="0" e="0" />
      <i d="2017/10/19" t="" p="19.2" a="300" f="b" c="5" x="0" e="0" />
      <i d="2017/10/30" t="" p="18.05" a="200" f="b" c="5" x="0" e="0" />
      <i d="2017/11/3" t="" p="19.98" a="200" f="s" c="5" x="4" e="0" />
      <i d="2017/11/6" t="" p="20.55" a="200" f="s" c="5" x="4.11" e="0" />
      <i d="2017/11/17" t="" p="23.32" a="300" f="s" c="5" x="7" e="0" />
    </recs>
    <advise />
  </stock>
  <stock id="sz300480" symbol="">
    <recs>
      <i d="2017/3/8" t="" p="26.1" a="200" f="b" c="5" x="0" e="0" />
      <i d="2017/3/9" t="" p="25.35" a="100" f="b" c="5" x="0" e="0" />
      <i d="2017/3/23" t="" p="26.7" a="300" f="s" c="5" x="8.01" e="0" />
    </recs>
    <advise />
  </stock>
  <stock id="sz002774" symbol="">
    <recs>
      <i d="2017/3/16" t="" p="6.1" a="500" f="b" c="0" x="0" e="0" />
      <i d="2017/8/29" t="" p="14.2" a="500" f="s" c="5" x="7.1" e="0" />
    </recs>
    <advise />
  </stock>
  <stock id="sz000898" symbol="">
    <recs>
      <i d="2017/8/29" t="" p="7.02" a="500" f="b" c="5" x="0" e="0" />
      <i d="2017/8/30" t="" p="7.35" a="500" f="s" c="5" x="3.68" e="0" />
    </recs>
    <advise />
  </stock>
  <stock id="sh601988" symbol="">
    <recs>
      <i d="2017/11/3" t="" p="3.85" a="1000" f="b" c="5" x="0.08" e="0" />
      <i d="2018/2/5" t="" p="4.75" a="1000" f="s" c="5" x="4.85" e="0" />
      <i d="2018/3/1" t="" p="4.24" a="1000" f="b" c="5" x="0.08" e="0" />
    </recs>
    <advise />
  </stock>
  <stock id="sh601633" symbol="">
    <recs>
      <i d="2017/11/7" t="" p="11.31" a="400" f="b" c="5" x="0.09" e="0" />
      <i d="2018/1/2" t="" p="12.26" a="400" f="s" c="5" x="5" e="0" />
    </recs>
    <advise />
  </stock>
  <stock id="sh600068" symbol="">
    <recs>
      <i d="2018/1/31" t="" p="9.49" a="500" f="b" c="5" x="0.09" e="0" />
      <i d="2018/2/1" t="" p="9.21" a="500" f="b" c="5" x="0.09" e="0" />
      <i d="2018/2/26" t="" p="9.31" a="500" f="s" c="5" x="4.75" e="0" />
    </recs>
    <advise />
  </stock>
  <stock id="sz002419" symbol="">
    <recs>
      <i d="2018/2/2" t="" p="17.39" a="500" f="b" c="5" x="0" e="0" />
      <i d="2018/2/5" t="" p="19.173" a="400" f="s" c="5" x="7.67" e="0" />
      <i d="2018/2/27" t="" p="19.15" a="100" f="s" c="5" x="1.92" e="0" />
    </recs>
    <advise />
  </stock>
</root>